CHANGES.txt
README.txt
buildout.cfg
setup.py
van/__init__.py
van.reposync.egg-info/PKG-INFO
van.reposync.egg-info/SOURCES.txt
van.reposync.egg-info/dependency_links.txt
van.reposync.egg-info/entry_points.txt
van.reposync.egg-info/namespace_packages.txt
van.reposync.egg-info/not-zip-safe
van.reposync.egg-info/requires.txt
van.reposync.egg-info/top_level.txt
van/reposync/README.txt
van/reposync/__init__.py
van/reposync/tests/__init__.py
van/reposync/tests/sources1.list
van/reposync/tests/sources_empty.list
van/reposync/tests/sync.txt
van/reposync/tests/test_doctest.py
van/reposync/tests/sample_repo1/Packages
van/reposync/tests/sample_repo1/Sources
van/reposync/tests/sample_repo1/build-dep-on-setuptools-without-egg-info_1-1.diff.gz
van/reposync/tests/sample_repo1/build-dep-on-setuptools-without-egg-info_1-1.dsc
van/reposync/tests/sample_repo1/build-dep-on-setuptools-without-egg-info_1.orig.tar.gz
van/reposync/tests/sample_repo1/python-build-dep-on-setuptools-without-egg-info_1-1_all.deb
van/reposync/tests/sample_repo1/python-van.pydeb_1.2.0-3_all.deb
van/reposync/tests/sample_repo1/python-zope.component-zcml_3.7.0-1_all.deb
van/reposync/tests/sample_repo1/python-zope.component_3.7.0-1_all.deb
van/reposync/tests/sample_repo1/update
van/reposync/tests/sample_repo1/van.pydeb_1.2.0-3.diff.gz
van/reposync/tests/sample_repo1/van.pydeb_1.2.0-3.dsc
van/reposync/tests/sample_repo1/van.pydeb_1.2.0.orig.tar.gz
van/reposync/tests/sample_repo1/zope.component_3.7.0-1.diff.gz
van/reposync/tests/sample_repo1/zope.component_3.7.0-1.dsc
van/reposync/tests/sample_repo1/zope.component_3.7.0.orig.tar.gz
van/reposync/tests/sample_repo_empty/Packages
van/reposync/tests/sample_repo_empty/Sources