Metadata-Version: 1.0
Name: van.reposync
Version: 1.0.1
Summary: Mirror a pypi-style egg repository from a debian APT repository
Home-page: http://pypi.python.org/pypi/van.reposync
Author: Vanguardistas
Author-email: UNKNOWN
License: ZPL 2.1
Platform: UNKNOWN
Classifier: Development Status :: 4 - Beta
Classifier: Intended Audience :: Developers
Classifier: Intended Audience :: System Administrators
Classifier: Topic :: System :: Archiving :: Packaging
Classifier: License :: DFSG approved
Classifier: License :: OSI Approved :: Zope Public License
Classifier: Operating System :: POSIX :: Linux
Classifier: Programming Language :: Python
